{
    "Ar36": {
        "error": 0.00027695524140951787,
        "error_type": "SEM",
        "filter_outliers_dict": {
            "filter_outliers": false,
            "iterations": 1,
            "std_devs": 2,
            "use_standard_deviation_filtering": false
        },
        "fit": "parabolic",
        "value": 0.002995170105052105
    },
    "Ar37": {
        "error": 0.000483782078829205,
        "error_type": "SEM",
        "filter_outliers_dict": {
            "filter_outliers": false,
            "iterations": 1,
            "std_devs": 2,
            "use_standard_deviation_filtering": false
        },
        "fit": "linear",
        "value": 0.019231623023707418
    },
    "Ar38": {
        "error": 0.000766749878752111,
        "error_type": "SEM",
        "filter_outliers_dict": {
            "filter_outliers": false,
            "iterations": 1,
            "std_devs": 2,
            "use_standard_deviation_filtering": false
        },
        "fit": "linear",
        "value": 0.08862513644502215
    },
    "Ar39": {
        "error": 0.010338908356679668,
        "error_type": "SEM",
        "filter_outliers_dict": {
            "filter_outliers": false,
            "iterations": 1,
            "std_devs": 2,
            "use_standard_deviation_filtering": false
        },
        "fit": "parabolic",
        "value": 7.07581563591326
    },
    "Ar40": {
        "error": 0.05167196247813375,
        "error_type": "SEM",
        "filter_outliers_dict": {
            "filter_outliers": false,
            "iterations": 1,
            "std_devs": 2,
            "use_standard_deviation_filtering": false
        },
        "fit": "parabolic",
        "value": 99.30028744650744
    },
    "Ar41": {
        "error": 0.013005311313576646,
        "error_type": "SEM",
        "filter_outliers_dict": {
            "filter_outliers": false,
            "iterations": 1,
            "std_devs": 2,
            "use_standard_deviation_filtering": false
        },
        "fit": "average",
        "value": -0.08433217338984832
    }
}