{
    "Ar36": {
        "error": 0.0001554588697540942,
        "error_type": "SEM",
        "filter_outliers_dict": {
            "filter_outliers": true,
            "iterations": 1,
            "std_devs": 2,
            "use_standard_deviation_filtering": false
        },
        "fit": "parabolic",
        "value": 0.00829871539003309
    },
    "Ar37": {
        "error": 0.01023820884717709,
        "error_type": "SEM",
        "filter_outliers_dict": {
            "filter_outliers": true,
            "iterations": 1,
            "std_devs": 2,
            "use_standard_deviation_filtering": false
        },
        "fit": "linear",
        "value": 0.029159402172503405
    },
    "Ar38": {
        "error": 0.013830353389399003,
        "error_type": "SEM",
        "filter_outliers_dict": {
            "filter_outliers": true,
            "iterations": 1,
            "std_devs": 2,
            "use_standard_deviation_filtering": false
        },
        "fit": "linear",
        "value": 0.12133422902951083
    },
    "Ar39": {
        "error": 0.00777079494145584,
        "error_type": "SEM",
        "filter_outliers_dict": {
            "filter_outliers": true,
            "iterations": 1,
            "std_devs": 2,
            "use_standard_deviation_filtering": false
        },
        "fit": "parabolic",
        "value": 17.342285511488367
    },
    "Ar40": {
        "error": 0.015886608641072223,
        "error_type": "SEM",
        "filter_outliers_dict": {
            "filter_outliers": true,
            "iterations": 1,
            "std_devs": 2,
            "use_standard_deviation_filtering": false
        },
        "fit": "parabolic",
        "value": 5.113760159872868
    },
    "Ar41": {
        "error": 0.009477475332190961,
        "error_type": "SEM",
        "filter_outliers_dict": {
            "filter_outliers": true,
            "iterations": 1,
            "std_devs": 2,
            "use_standard_deviation_filtering": false
        },
        "fit": "linear",
        "value": 0.25335065995608214
    }
}