{
    "Ar36": {
        "error": 0.0011156657364006356,
        "error_type": "SD",
        "filter_outliers_dict": {
            "filter_outliers": false,
            "iterations": 1,
            "std_devs": 1,
            "use_standard_deviation_filtering": false
        },
        "fit": "parabolic",
        "value": 0.0058026304816991316
    },
    "Ar37": {
        "error": 0.1313532883816137,
        "error_type": "SD",
        "filter_outliers_dict": {
            "filter_outliers": false,
            "iterations": 1,
            "std_devs": 1,
            "use_standard_deviation_filtering": false
        },
        "fit": "linear",
        "value": 0.04927854235754283
    },
    "Ar38": {
        "error": 0.14941720210828913,
        "error_type": "SD",
        "filter_outliers_dict": {
            "filter_outliers": false,
            "iterations": 1,
            "std_devs": 1,
            "use_standard_deviation_filtering": false
        },
        "fit": "linear",
        "value": 0.06212693319314051
    },
    "Ar39": {
        "error": 0.06231513762713306,
        "error_type": "SD",
        "filter_outliers_dict": {
            "filter_outliers": false,
            "iterations": 1,
            "std_devs": 1,
            "use_standard_deviation_filtering": false
        },
        "fit": "parabolic",
        "value": 9.526199487762707
    },
    "Ar40": {
        "error": 0.1299532877907461,
        "error_type": "SD",
        "filter_outliers_dict": {
            "filter_outliers": false,
            "iterations": 1,
            "std_devs": 1,
            "use_standard_deviation_filtering": false
        },
        "fit": "parabolic",
        "value": 3.16356280463528
    },
    "Ar41": {
        "error": 0.13518016840338115,
        "error_type": "SD",
        "filter_outliers_dict": {
            "filter_outliers": false,
            "iterations": 1,
            "std_devs": 1,
            "use_standard_deviation_filtering": false
        },
        "fit": "average_SEM",
        "value": 0.27113244110601953
    }
}