{
    "AX": {
        "error": 0.010237190223715479,
        "error_type": "SEM",
        "filter_outliers_dict": {
            "filter_outliers": true,
            "iterations": 1,
            "std_devs": 2,
            "use_standard_deviation_filtering": false
        },
        "fit": "average",
        "value": -0.0539430850603355
    },
    "CDD": {
        "error": 1.2151875265758869e-05,
        "error_type": "SEM",
        "filter_outliers_dict": {
            "filter_outliers": true,
            "iterations": 1,
            "std_devs": 2,
            "use_standard_deviation_filtering": false
        },
        "fit": "average",
        "value": 0.0001488094906444135
    },
    "H1": {
        "error": 0.010196496107236287,
        "error_type": "SEM",
        "filter_outliers_dict": {
            "filter_outliers": true,
            "iterations": 1,
            "std_devs": 2,
            "use_standard_deviation_filtering": false
        },
        "fit": "average",
        "value": 0.03597048806689639
    },
    "H2": {
        "error": 0.010548160081672113,
        "error_type": "SEM",
        "filter_outliers_dict": {
            "filter_outliers": true,
            "iterations": 1,
            "std_devs": 2,
            "use_standard_deviation_filtering": false
        },
        "fit": "average",
        "value": 0.18849904016571362
    },
    "L1": {
        "error": 0.010234271563311914,
        "error_type": "SEM",
        "filter_outliers_dict": {
            "filter_outliers": true,
            "iterations": 1,
            "std_devs": 2,
            "use_standard_deviation_filtering": false
        },
        "fit": "average",
        "value": -0.14443357294760317
    },
    "L2": {
        "error": 0.009437802106785836,
        "error_type": "SEM",
        "filter_outliers_dict": {
            "filter_outliers": true,
            "iterations": 1,
            "std_devs": 2,
            "use_standard_deviation_filtering": false
        },
        "fit": "average",
        "value": 0.10331921570293068
    }
}