{
    "Ar36": {
        "error": 0.0008768076388370312,
        "error_type": "SD",
        "filter_outliers_dict": {
            "filter_outliers": true,
            "iterations": 1,
            "std_devs": 2,
            "use_standard_deviation_filtering": false
        },
        "fit": "Parabolic",
        "fn": 382,
        "include_baseline_error": false,
        "n": 400,
        "outlier_excluded": [
            160,
            193,
            225,
            99,
            256,
            261,
            44,
            141,
            206,
            80,
            49,
            18,
            84,
            277,
            152,
            155,
            283,
            31
        ],
        "reviewed": true,
        "user_excluded": [],
        "value": 0.2946988572246956
    },
    "Ar37": {
        "error": 0.012422687929612979,
        "error_type": "SD",
        "filter_outliers_dict": {
            "filter_outliers": true,
            "iterations": 1,
            "std_devs": 2,
            "use_standard_deviation_filtering": false
        },
        "fit": "Linear",
        "fn": 386,
        "include_baseline_error": false,
        "n": 400,
        "outlier_excluded": [
            130,
            328,
            203,
            48,
            208,
            19,
            148,
            182,
            247,
            216,
            342,
            58,
            284,
            158
        ],
        "reviewed": true,
        "user_excluded": [],
        "value": -0.00158985485922398
    },
    "Ar38": {
        "error": 0.01427641190012265,
        "error_type": "SD",
        "filter_outliers_dict": {
            "filter_outliers": true,
            "iterations": 1,
            "std_devs": 2,
            "use_standard_deviation_filtering": false
        },
        "fit": "Linear",
        "fn": 385,
        "include_baseline_error": false,
        "n": 400,
        "outlier_excluded": [
            160,
            287,
            293,
            103,
            40,
            9,
            168,
            330,
            361,
            150,
            120,
            314,
            27,
            221,
            159
        ],
        "reviewed": true,
        "user_excluded": [],
        "value": -0.011505861520335201
    },
    "Ar39": {
        "error": 0.008865698636944308,
        "error_type": "SD",
        "filter_outliers_dict": {
            "filter_outliers": true,
            "iterations": 1,
            "std_devs": 2,
            "use_standard_deviation_filtering": false
        },
        "fit": "Parabolic",
        "fn": 380,
        "include_baseline_error": false,
        "n": 400,
        "outlier_excluded": [
            64,
            285,
            318,
            100,
            360,
            172,
            365,
            207,
            335,
            113,
            275,
            116,
            372,
            312,
            185,
            27,
            187,
            219,
            30,
            284
        ],
        "reviewed": true,
        "user_excluded": [],
        "value": 0.03205574296441277
    },
    "Ar40": {
        "error": 0.0256775950380397,
        "error_type": "SD",
        "filter_outliers_dict": {
            "filter_outliers": true,
            "iterations": 1,
            "std_devs": 2,
            "use_standard_deviation_filtering": false
        },
        "fit": "Parabolic",
        "fn": 383,
        "include_baseline_error": false,
        "n": 400,
        "outlier_excluded": [
            260,
            229,
            166,
            135,
            294,
            325,
            361,
            392,
            240,
            49,
            369,
            148,
            213,
            182,
            246,
            25,
            218
        ],
        "reviewed": true,
        "user_excluded": [],
        "value": 89.3508711364446
    },
    "Ar41": {
        "error": 0.14516802977603266,
        "error_type": "SD",
        "filter_outliers_dict": {
            "filter_outliers": false,
            "iterations": 1,
            "std_devs": 1,
            "use_standard_deviation_filtering": false
        },
        "fit": "average_SEM",
        "value": 0.0005215645229327493
    }
}